stix_shifter_modules/azure_log_analytics/__init__.py
stix_shifter_modules/azure_log_analytics/entry_point.py
stix_shifter_modules/azure_log_analytics/configuration/config.json
stix_shifter_modules/azure_log_analytics/configuration/dialects.json
stix_shifter_modules/azure_log_analytics/configuration/lang_en.json
stix_shifter_modules/azure_log_analytics/stix_translation/__init__.py
stix_shifter_modules/azure_log_analytics/stix_translation/json_to_stix_translator.py
stix_shifter_modules/azure_log_analytics/stix_translation/query_constructor.py
stix_shifter_modules/azure_log_analytics/stix_translation/query_translator.py
stix_shifter_modules/azure_log_analytics/stix_translation/transformers.py
stix_shifter_modules/azure_log_analytics/stix_translation/json/SecurityAlert_from_stix_map.json
stix_shifter_modules/azure_log_analytics/stix_translation/json/SecurityEvent_from_stix_map.json
stix_shifter_modules/azure_log_analytics/stix_translation/json/SecurityIncident_from_stix_map.json
stix_shifter_modules/azure_log_analytics/stix_translation/json/config_map.json
stix_shifter_modules/azure_log_analytics/stix_translation/json/operators.json
stix_shifter_modules/azure_log_analytics/stix_translation/json/to_stix_map.json
stix_shifter_modules/azure_log_analytics/stix_translation/json/stix_2_1/SecurityAlert_from_stix_map.json
stix_shifter_modules/azure_log_analytics/stix_translation/json/stix_2_1/SecurityEvent_from_stix_map.json
stix_shifter_modules/azure_log_analytics/stix_translation/json/stix_2_1/SecurityIncident_from_stix_map.json
stix_shifter_modules/azure_log_analytics/stix_translation/json/stix_2_1/to_stix_map.json
stix_shifter_modules/azure_log_analytics/stix_transmission/__init__.py
stix_shifter_modules/azure_log_analytics/stix_transmission/api_client.py
stix_shifter_modules/azure_log_analytics/stix_transmission/connector.py
stix_shifter_modules/azure_log_analytics/stix_transmission/error_mapper.py
stix_shifter_modules_azure_log_analytics-8.0.2.dist-info/licenses/AUTHORS.md
stix_shifter_modules_azure_log_analytics-8.0.2.dist-info/licenses/LICENSE.md
stix_shifter_modules_azure_log_analytics-8.0.2.dist-info/licenses/NOTICE
stix_shifter_modules_azure_log_analytics-8.0.2.dist-info/METADATA
stix_shifter_modules_azure_log_analytics-8.0.2.dist-info/WHEEL
stix_shifter_modules_azure_log_analytics-8.0.2.dist-info/top_level.txt
stix_shifter_modules_azure_log_analytics-8.0.2.dist-info/RECORD
