Metadata-Version: 2.4
Name: stix_shifter_modules_azure_log_analytics
Version: 8.0.2
Summary: Tools and interface to translate STIX formatted results and queries to different data source formats and to set up appropriate connection strings for invoking and triggering actions in openwhisk
Author: ibm
License-Expression: Apache-2.0
Project-URL: Homepage, https://github.com/opencybersecurityalliance/stix-shifter
Project-URL: Source, https://github.com/opencybersecurityalliance/stix-shifter
Keywords: datasource,stix,translate,transform,transmit
Classifier: Programming Language :: Python :: 3.10
Classifier: Programming Language :: Python :: 3.11
Classifier: Programming Language :: Python :: 3.12
Requires-Python: >=3.10
License-File: LICENSE.md
License-File: AUTHORS.md
License-File: NOTICE
Requires-Dist: azure-monitor-query==1.0.2
Requires-Dist: jsonref==1.1.0
Requires-Dist: numpy<1.27,>=1.26
Requires-Dist: pandas==1.5.2
Dynamic: license-file
